<?xml version="1.0"?>
<!DOCTYPE hibernate-mapping PUBLIC "-//Hibernate/Hibernate Mapping DTD 3.0//EN"
"http://hibernate.sourceforge.net/hibernate-mapping-3.0.dtd">
<!-- Generated 13 Feb, 2015 11:07:05 AM by Hibernate Tools 3.4.0.CR1 -->
<hibernate-mapping>
    <class name="com.ainosoft.demo.pojo.Addressbook" table="Addressbook" catalog="viewdb">
        <id name="bookId" type="java.lang.Integer">
            <column name="book_id" />
            <generator class="identity" />
        </id>
        <property name="bookName" type="string">
            <column name="book_name" length="45" />
        </property>
    </class>
</hibernate-mapping>
